<?xml version="1.0" encoding="UTF-8"?>

<!-- generated on 2025-12-05 17:25:10 by Eclipse SUMO GUI Version 1.24.0
<sumoConfiguration xmlns:xsi="http://www.w3.org/2001/XMLSchema-instance" xsi:noNamespaceSchemaLocation="http://sumo.dlr.de/xsd/sumoConfiguration.xsd">

    <input>
        <net-file value="sumo_files/RL.net.xml"/>
        <route-files value="sumo_files/RL.rou.xml"/>
        <additional-files value="sumo_files/RL.add.xml"/>
        <junction-taz value="true"/>
    </input>

    <time>
        <step-length value="1.0"/>
    </time>

    <traci_server>
        <remote-port value="56151"/>
    </traci_server>

</sumoConfiguration>
-->

<detector xmlns:xsi="http://www.w3.org/2001/XMLSchema-instance" xsi:noNamespaceSchemaLocation="http://sumo.dlr.de/xsd/det_e2_file.xsd">
   <interval begin="0.00" end="300.00" id="Node2_7_SB_0" sampledSeconds="703.60" nVehEntered="45" nVehLeft="42" nVehSeen="45" meanSpeed="1.55" meanTimeLoss="13.87" meanOccupancy="53.50" maxOccupancy="71.03" meanMaxJamLengthInVehicles="1.66" meanMaxJamLengthInMeters="10.44" maxJamLengthInVehicles="3" maxJamLengthInMeters="19.40" jamLengthInVehiclesSum="498" jamLengthInMetersSum="3132.70" meanHaltingDuration="23.64" maxHaltingDuration="48.00" haltingDurationSum="520.00" meanIntervalHaltingDuration="23.64" maxIntervalHaltingDuration="48.00" intervalHaltingDurationSum="520.00" startedHalts="22.00" meanVehicleNumber="2.49" maxVehicleNumber="3" />
   <interval begin="0.00" end="300.00" id="e2_3" sampledSeconds="128.54" nVehEntered="5" nVehLeft="3" nVehSeen="5" meanSpeed="0.12" meanTimeLoss="25.49" meanOccupancy="5.79" maxOccupancy="37.76" meanMaxJamLengthInVehicles="0.40" meanMaxJamLengthInMeters="1.14" maxJamLengthInVehicles="2" maxJamLengthInMeters="10.15" jamLengthInVehiclesSum="119" jamLengthInMetersSum="341.96" meanHaltingDuration="24.80" maxHaltingDuration="37.00" haltingDurationSum="124.00" meanIntervalHaltingDuration="24.80" maxIntervalHaltingDuration="37.00" intervalHaltingDurationSum="124.00" startedHalts="5.00" meanVehicleNumber="0.44" maxVehicleNumber="2" />
   <interval begin="300.00" end="594.00" id="Node2_7_SB_0" sampledSeconds="704.17" nVehEntered="47" nVehLeft="49" nVehSeen="50" meanSpeed="1.70" meanTimeLoss="12.33" meanOccupancy="54.07" maxOccupancy="71.01" meanMaxJamLengthInVehicles="1.58" meanMaxJamLengthInMeters="9.95" maxJamLengthInVehicles="3" maxJamLengthInMeters="19.48" jamLengthInVehiclesSum="464" jamLengthInMetersSum="2926.17" meanHaltingDuration="26.95" maxHaltingDuration="47.00" haltingDurationSum="566.00" meanIntervalHaltingDuration="22.95" maxIntervalHaltingDuration="47.00" intervalHaltingDurationSum="482.00" startedHalts="18.00" meanVehicleNumber="2.54" maxVehicleNumber="3" />
   <interval begin="300.00" end="594.00" id="e2_3" sampledSeconds="182.12" nVehEntered="4" nVehLeft="6" nVehSeen="6" meanSpeed="0.16" meanTimeLoss="29.99" meanOccupancy="8.91" maxOccupancy="37.76" meanMaxJamLengthInVehicles="0.57" meanMaxJamLengthInMeters="1.98" maxJamLengthInVehicles="2" maxJamLengthInMeters="10.05" jamLengthInVehiclesSum="169" jamLengthInMetersSum="583.18" meanHaltingDuration="33.83" maxHaltingDuration="42.00" haltingDurationSum="203.00" meanIntervalHaltingDuration="28.83" maxIntervalHaltingDuration="42.00" intervalHaltingDurationSum="173.00" startedHalts="4.00" meanVehicleNumber="0.63" maxVehicleNumber="2" />
</detector>
